LICENSE
pyxrayc/__init__.py
pyxrayc/__main__.py
pyxrayc/cli/__init__.py
pyxrayc/cli/main.py
pyxrayc/config.py
pyxrayc/enums.py
pyxrayc/py.typed
pyxrayc/types.py
pyxrayc/utils.py
pyxrayc-0.1.3.dist-info/entry_points.txt
pyxrayc-0.1.3.dist-info/LICENSE
pyxrayc-0.1.3.dist-info/WHEEL
pyxrayc-0.1.3.dist-info/METADATA
pyxrayc-0.1.3.dist-info/RECORD
