Metadata-Version: 2.1
Name: pyxrayc
Version: 0.1.3
Summary: CLI utility for managing Xray VPN server user accounts with ease, written in Python.
Home-page: https://github.com/PlumaCompanyLtd/PyXrayC
License: GPL-3.0-only
Keywords: xray,cli,management
Author: Seyed
Author-email: pyseyed@gmail.com
Requires-Python: >=3.8,<4.0
Classifier: Intended Audience :: Developers
Classifier: Intended Audience :: System Administrators
Classifier: License :: OSI Approved :: GNU General Public License v3 (GPLv3)
Classifier: Operating System :: POSIX :: Linux
Classifier: Programming Language :: Python :: 3
Classifier: Programming Language :: Python :: 3.8
Classifier: Programming Language :: Python :: 3.9
Classifier: Programming Language :: Python :: 3.10
Classifier: Programming Language :: Python :: 3.11
Classifier: Programming Language :: Python :: 3 :: Only
Classifier: Programming Language :: Python :: 3.10
Classifier: Programming Language :: Python :: 3.8
Classifier: Programming Language :: Python :: 3.9
Classifier: Topic :: Software Development :: Libraries :: Python Modules
Classifier: Typing :: Typed
Requires-Dist: python-decouple (>=3.6,<4.0)
Requires-Dist: typer[all] (>=0.7.0,<0.8.0)
Requires-Dist: typing-extensions (>=4.4.0,<5.0.0)
Requires-Dist: ujson (>=5.6.0,<6.0.0)
Project-URL: Bug Tracker, https://github.com/PlumaCompanyLtd/PyXrayC/issues
Project-URL: Repository, https://github.com/PlumaCompanyLtd/PyXrayC
